CHANGES.txt
MANIFEST.in
README.md
setup.cfg
setup.py
trac/__init__.py
trac.por.egg-info/PKG-INFO
trac.por.egg-info/SOURCES.txt
trac.por.egg-info/dependency_links.txt
trac.por.egg-info/entry_points.txt
trac.por.egg-info/namespace_packages.txt
trac.por.egg-info/not-zip-safe
trac.por.egg-info/requires.txt
trac.por.egg-info/top_level.txt
trac/por/__init__.py
trac/por/communication.py
trac/por/i18n.py
trac/por/monkey.py
trac/por/plugins.py
trac/por/trac-rescope.py
trac/por/user.py
trac/por/workflow.py
trac/por/htdocs/por.css
trac/por/htdocs/por.js
trac/por/htdocs/rescoped-css/about.css
trac/por/htdocs/rescoped-css/admin.css
trac/por/htdocs/rescoped-css/browser.css
trac/por/htdocs/rescoped-css/changeset.css
trac/por/htdocs/rescoped-css/code.css
trac/por/htdocs/rescoped-css/diff.css
trac/por/htdocs/rescoped-css/prefs.css
trac/por/htdocs/rescoped-css/report.css
trac/por/htdocs/rescoped-css/roadmap.css
trac/por/htdocs/rescoped-css/search.css
trac/por/htdocs/rescoped-css/ticket.css
trac/por/htdocs/rescoped-css/timeline.css
trac/por/htdocs/rescoped-css/trac.css
trac/por/htdocs/rescoped-css/wiki.css
trac/por/locale/messages.pot
trac/por/locale/en/LC_MESSAGES/trac.por.po
trac/por/locale/it/LC_MESSAGES/trac.por.po
trac/por/templates/admin-communication.html
trac/por/templates/por_theme.html
trac/por/tests/__init__.py
trac/por/tests/test_notification.py