Metadata-Version: 1.0
Name: trac.por
Version: 1.2.19
Summary: Penelope: trac integration
Home-page: http://getpenelope.github.com
Author: Penelope Team
Author-email: penelopedev@redturtle.it
License: UNKNOWN
Keywords: web trac
Platform: UNKNOWN
Classifier: Programming Language :: Python
Classifier: Framework :: Trac
Classifier: Topic :: Internet :: WWW/HTTP
Classifier: Topic :: Internet :: WWW/HTTP :: WSGI :: Application
